nsa_flow/__init__.py
nsa_flow/core.py
tests/basic_nsa_test.py
tests/degug.py
tests/run_nsa_flow_tests.py
tests/test_energy_behavior.py
tests/test_nsa_autograd.py
tests/test_nsa_flow_extended.py
tests/test_nsa_flow_opt.py
tests/test_nsa_flow_parameters.py
tests/test_nsaf_layer.py
nsa_flow-0.9.0.dist-info/METADATA
nsa_flow-0.9.0.dist-info/WHEEL
nsa_flow-0.9.0.dist-info/top_level.txt
nsa_flow-0.9.0.dist-info/RECORD
