Metadata-Version: 2.1
Name: nsa-flow
Version: 0.9.0
Summary: Non-negative Stiefel Approximating Flow for interpretable representation learning
Author-email: "B. Avants" <stnava@example.com>
License: MIT
Project-URL: Homepage, https://github.com/stnava/nsa_flow
Project-URL: Repository, https://github.com/stnava/nsa_flow
Requires-Python: >=3.9
Requires-Dist: torch>=2.0
Requires-Dist: numpy>=1.23
Requires-Dist: matplotlib>=3.7
Requires-Dist: pandas>=1.5
Requires-Dist: torch-optimizer>=0.3.0
